hausastemmer/HausaStemmer.py
hausastemmer/__about__.py
hausastemmer/__init__.py
hausastemmer/dict_lookup.py
hausastemmer-1.0.dist-info/DESCRIPTION.rst
hausastemmer-1.0.dist-info/METADATA
hausastemmer-1.0.dist-info/RECORD
hausastemmer-1.0.dist-info/WHEEL
hausastemmer-1.0.dist-info/metadata.json
hausastemmer-1.0.dist-info/top_level.txt
