Metadata-Version: 2.0
Name: hausastemmer
Version: 1.0
Summary: Hausa language stemmer (Bimba et al., 2015)
Home-page: https://github.com/berkmancenter/mediacloud-hausastemmer
Author: Andrew Bimba, Norisma Idris, Norazlina Khamis, Nurul Fazmidar Mohd Noor, Linas Valiukas
Author-email: andrewbimba@gmail.com, lvaliukas@cyber.law.harvard.edu
License: BSD
Keywords: hausa stemmer bimba
Platform: UNKNOWN
Classifier: Development Status :: 3 - Alpha
Classifier: Intended Audience :: Developers
Classifier: Intended Audience :: Information Technology
Classifier: License :: OSI Approved :: GNU General Public License v3 or later (GPLv3+)
Classifier: Programming Language :: Python
Classifier: Operating System :: OS Independent
Classifier: Programming Language :: Python :: 2.7
Classifier: Programming Language :: Python :: 3.3
Classifier: Programming Language :: Python :: 3.5
Classifier: Programming Language :: Python :: 3.6
Classifier: Programming Language :: Python :: Implementation :: PyPy
Classifier: Topic :: Database
Classifier: Topic :: Internet :: WWW/HTTP :: Indexing/Search
Classifier: Topic :: Text Processing :: Indexing
Classifier: Topic :: Text Processing :: Linguistic
